LICENSE-APACHE
LICENSE-MIT
README.md
pyproject.toml
hibiki/__init__.py
hibiki.egg-info/PKG-INFO
hibiki.egg-info/SOURCES.txt
hibiki.egg-info/dependency_links.txt
hibiki.egg-info/requires.txt
hibiki.egg-info/top_level.txt